<annotation>
	<folder>input</folder>
	<filename>new-143.jpg</filename>
	<path>/Users/saleem/code/fireaiot/brain/input/new-143.jpg</path>
	<source>
		<database>Unknown</database>
	</source>
	<size>
		<width>2048</width>
		<height>1536</height>
		<depth>3</depth>
	</size>
	<segmented>0</segmented>
	<object>
		<name>fire</name>
		<pose>Unspecified</pose>
		<truncated>0</truncated>
		<difficult>0</difficult>
		<bndbox>
			<xmin>74</xmin>
			<ymin>424</ymin>
			<xmax>572</xmax>
			<ymax>879</ymax>
		</bndbox>
	</object>
</annotation>
